{
  "kind": "collectionType",
  "collectionName": "posts",
  "info": {
    "singularName": "post",
    "pluralName": "posts",
    "displayName": "Post",
    "description": ""
  },
  "options": {
    "draftAndPublish": true
  },
  "pluginOptions": {},
  "attributes": {
    "Title": {
      "type": "string"
    },
    "Date": {
      "type": "date"
    },
    "ShortDescription": {
      "type": "richtext"
    },
    "posts": {
      "type": "relation",
      "relation": "oneToMany",
      "target": "api::post.post"
    }
  }
}
